tradingcornerstone/__init__.py
tradingcornerstone_pre_alpha-0.0.2.dist-info/METADATA
tradingcornerstone_pre_alpha-0.0.2.dist-info/WHEEL
tradingcornerstone_pre_alpha-0.0.2.dist-info/top_level.txt
tradingcornerstone_pre_alpha-0.0.2.dist-info/RECORD
