Metadata-Version: 2.4
Name: tradingcornerstone-pre-alpha
Version: 0.0.2
Summary: A minimal PyPI test package
Author-email: Your Name <your@email.com>
